url_to_sql_project/__init__.py
url_to_sql_project/main.py
url_to_sql_project-0.1.0.dist-info/METADATA
url_to_sql_project-0.1.0.dist-info/WHEEL
url_to_sql_project-0.1.0.dist-info/RECORD
